collective.contactformprotection-1.1.0-py3.12-nspkg.pth
collective/contactformprotection/__init__.py
collective/contactformprotection/configure.zcml
collective/contactformprotection/controlpanel.py
collective/contactformprotection/interfaces.py
collective/contactformprotection/permissions.zcml
collective/contactformprotection/setuphandlers.py
collective/contactformprotection/testing.py
collective/contactformprotection/vocabulary.py
collective/contactformprotection/browser/__init__.py
collective/contactformprotection/browser/configure.zcml
collective/contactformprotection/browser/contact-form.pt
collective/contactformprotection/browser/contactform.py
collective/contactformprotection/locales/README.rst
collective/contactformprotection/locales/__init__.py
collective/contactformprotection/locales/collective.contactformprotection.pot
collective/contactformprotection/locales/update.py
collective/contactformprotection/locales/update.sh
collective/contactformprotection/locales/de/LC_MESSAGES/collective.contactformprotection.po
collective/contactformprotection/locales/en/LC_MESSAGES/collective.contactformprotection.po
collective/contactformprotection/profiles/default/browserlayer.xml
collective/contactformprotection/profiles/default/controlpanel.xml
collective/contactformprotection/profiles/default/metadata.xml
collective/contactformprotection/profiles/default/registry.xml
collective/contactformprotection/profiles/uninstall/browserlayer.xml
collective/contactformprotection/profiles/uninstall/controlpanel.xml
collective/contactformprotection/profiles/uninstall/registry.xml
collective/contactformprotection/tests/__init__.py
collective/contactformprotection/tests/test_contacform.py
collective/contactformprotection/tests/test_setup.py
collective/contactformprotection/tests/test_vocab_captcha_vocabulary.py
collective_contactformprotection-1.1.0.dist-info/LICENSE.GPL
collective_contactformprotection-1.1.0.dist-info/LICENSE.rst
collective_contactformprotection-1.1.0.dist-info/METADATA
collective_contactformprotection-1.1.0.dist-info/WHEEL
collective_contactformprotection-1.1.0.dist-info/entry_points.txt
collective_contactformprotection-1.1.0.dist-info/namespace_packages.txt
collective_contactformprotection-1.1.0.dist-info/top_level.txt
collective_contactformprotection-1.1.0.dist-info/RECORD
