Metadata-Version: 2.2
Name: collective.contactformprotection
Version: 1.1.0
Summary: This package protects the default contact form of Plone which is generally accessible via /contact-form. It provides a checkbox in the controlpanel to disable it globally and adds a (H/Re)captcha field depending on your installation.
Home-page: https://github.com/collective/collective.contactformprotection
Author: Peter Mathis
Author-email: peter.mathis@kombinat.at
License: GPL version 3
Project-URL: PyPI, https://pypi.org/project/collective.contactformprotection/
Project-URL: Source, https://github.com/collective/collective.contactformprotection
Project-URL: Tracker, https://github.com/collective/collective.contactformprotection/issues
Keywords: Python Plone CMS
Classifier: Development Status :: 5 - Production/Stable
Classifier: Environment :: Web Environment
Classifier: Framework :: Plone
Classifier: Framework :: Plone :: Addon
Classifier: Framework :: Plone :: 6.0
Classifier: Programming Language :: Python
Classifier: Programming Language :: Python :: 3.8
Classifier: Programming Language :: Python :: 3.9
Classifier: Programming Language :: Python :: 3.10
Classifier: Programming Language :: Python :: 3.11
Classifier: Programming Language :: Python :: 3.12
Classifier: Operating System :: OS Independent
Classifier: License :: OSI Approved :: GNU General Public License v2 (GPLv2)
Requires-Python: >=3.8
License-File: LICENSE.GPL
License-File: LICENSE.rst
Requires-Dist: setuptools
Requires-Dist: Products.CMFPlone
Requires-Dist: plone.api>=1.8.4
Requires-Dist: plone.app.dexterity
Requires-Dist: plone.app.registry
Requires-Dist: z3c.form
Provides-Extra: recaptcha
Requires-Dist: plone.formwidget.recaptcha; extra == "recaptcha"
Provides-Extra: hcaptcha
Requires-Dist: plone.formwidget.hcaptcha; extra == "hcaptcha"
Provides-Extra: norobots
Requires-Dist: collective.z3cform.norobots; extra == "norobots"
Provides-Extra: test
Requires-Dist: plone.app.testing; extra == "test"
Requires-Dist: plone.testing>=5.0.0; extra == "test"
Requires-Dist: plone.app.contenttypes; extra == "test"
Requires-Dist: plone.app.robotframework[debug]; extra == "test"
Requires-Dist: plone.formwidget.recaptcha; extra == "test"
Requires-Dist: plone.formwidget.hcaptcha; extra == "test"
Requires-Dist: collective.z3cform.norobots; extra == "test"
Dynamic: author
Dynamic: author-email
Dynamic: classifier
Dynamic: description
Dynamic: home-page
Dynamic: keywords
Dynamic: license
Dynamic: project-url
Dynamic: provides-extra
Dynamic: requires-dist
Dynamic: requires-python
Dynamic: summary
